<?xml version="1.0" encoding="utf-8" ?>
<Defs>
	<TabulaRasa.UpdateDef Abstract="true" Name="Prioritize_UpdateInfoBase">
		<linkUrl>https://steamcommunity.com/sharedfiles/filedetails/?id=3276664162</linkUrl>
		<banner>UpdateInfo/Prioritize</banner>
	</TabulaRasa.UpdateDef>
	<TabulaRasa.UpdateDef ParentName="Prioritize_UpdateInfoBase" MayRequire="neronix17.toolbox">
		<defName>Prioritize_1_6_0</defName>
		<date>2026/1/19</date>
		<content>This mod will not be further updated.</content>
	</TabulaRasa.UpdateDef>
</Defs>
